cv_toy/__init__.py
cv_toy/metrics/__init__.py
cv_toy/metrics/brisque.py
cv_toy/metrics/niqe.py
cv_toy/metrics/psnr.py
cv_toy/metrics/ssim.py
cv_toy/metrics/utils.py
cv_toy/requirements.txt
cv_toy/utils/__init__.py
cv_toy/utils/patches.py
cv_toy/utils/processing.py
cv_toy/utils/utils.py
cv_toy-0.1.0.dist-info/METADATA
cv_toy-0.1.0.dist-info/WHEEL
cv_toy-0.1.0.dist-info/RECORD
