Metadata-Version: 2.1
Name: cv_toy
Version: 0.1.0
Summary: 
Author: Ryabykin Aleksey
Author-email: ryabykin.as@yandex.ru
Requires-Python: >=3.9,<3.11
Classifier: Programming Language :: Python :: 3
Classifier: Programming Language :: Python :: 3.9
Classifier: Programming Language :: Python :: 3.10
Requires-Dist: numpy (==1.23.4)
Requires-Dist: opencv-python (==4.7.0.72)
Requires-Dist: requests (==2.28.1)
Requires-Dist: scikit-image (==0.19.3)
Requires-Dist: scipy (==1.8.1)
